MANIFEST.in
README.md
requirements-min-django.txt
requirements-test.txt
requirements.txt
setup.py
database_size/__init__.py
database_size/admin.py
database_size/apps.py
database_size/models.py
database_size/utils.py
database_size/sql/table.mysql.sql
database_size/sql/table.postgresql.sql
database_size/sql/table.sqlite.sql
database_size/sql/table.sqlite3.sql
database_size/tests/__init__.py
database_size/tests/manage.py
database_size/tests/models.py
database_size/tests/settings.py
database_size/tests/tests.py
database_size/tests/urls.py
database_size/tests/views.py
database_size/tests/management/__init__.py
database_size/tests/management/commands/__init__.py
django_database_size.egg-info/PKG-INFO
django_database_size.egg-info/SOURCES.txt
django_database_size.egg-info/dependency_links.txt
django_database_size.egg-info/requires.txt
django_database_size.egg-info/top_level.txt