Metadata-Version: 2.1
Name: django-database-size
Version: 1.0.5
Summary: Monitor the size of database tables from Django admin.
Home-page: http://github.com/chrisspen/django-database-size
Author: Chris Spencer
Author-email: chrisspen@gmail.com
License: UNKNOWN
Platform: UNKNOWN
Classifier: Development Status :: 5 - Production/Stable
Classifier: Framework :: Django
Classifier: Intended Audience :: Developers
Classifier: License :: OSI Approved :: BSD License
Classifier: Operating System :: OS Independent
Classifier: Programming Language :: Python
Classifier: Programming Language :: Python :: 2.7
Classifier: Programming Language :: Python :: 3.4
Classifier: Programming Language :: Python :: 3.5
Classifier: Programming Language :: Python :: 3.6
Classifier: Programming Language :: PL/SQL
